dimred/__init__.py
dimred/dimred.py
dimred-0.0.1.dist-info/LICENSE
dimred-0.0.1.dist-info/METADATA
dimred-0.0.1.dist-info/WHEEL
dimred-0.0.1.dist-info/top_level.txt
dimred-0.0.1.dist-info/RECORD
