Metadata-Version: 2.1
Name: dimred
Version: 0.0.1
Summary: Dimension Reduction and Visualization with PCA SVD, EVD and more
Home-page: https://github.com/FabG/dimred
Author: Fabrice Guillaume
Author-email: fabrice.guillaume@email.com
License: MIT
Platform: UNKNOWN
Classifier: Programming Language :: Python :: 3
Classifier: License :: OSI Approved :: MIT License
Classifier: Operating System :: OS Independent
Requires-Python: >=3.6
Requires-Dist: sklearn
Requires-Dist: numpy
Requires-Dist: pandas
Requires-Dist: matplotlib
Requires-Dist: scipy
Requires-Dist: colourmap
Requires-Dist: pytest
Requires-Dist: pytest-cov
Requires-Dist: seaborn
Requires-Dist: pathlib
